fine_python_recommended/__init__.py
fine_python_recommended/preset.toml
fine_python_recommended-0.4.0.dist-info/METADATA
fine_python_recommended-0.4.0.dist-info/WHEEL
fine_python_recommended-0.4.0.dist-info/top_level.txt
fine_python_recommended-0.4.0.dist-info/RECORD
