Metadata-Version: 2.4
Name: fine_python_recommended
Version: 0.4.0
Author-email: Vladyslav Hnatiuk <aders1234@gmail.com>
Requires-Python: <3.14,>=3.11
Requires-Dist: fine_python_format==0.3.*
Requires-Dist: fine_python_lint==0.4.*
